README.rst
setup.cfg
setup.py
src/pygradle/__init__.py
src/pygradle/gradlew.py
src/pygradle.egg-info/PKG-INFO
src/pygradle.egg-info/SOURCES.txt
src/pygradle.egg-info/dependency_links.txt
src/pygradle.egg-info/top_level.txt
src/tests/__init__.py
src/tests/integration/__init__.py
src/tests/integration/testinteg.py