Metadata-Version: 1.1
Name: pygradle
Version: 0.1.dev0
Summary: Python gradle wrapper
Home-page: https://github.com/mwalkowski/pygradle
Author: Michal Walkowski
Author-email: mi.walkowski@gmail.com
License: Apache 2.0
Keywords: java gradle
Platform: UNKNOWN
Classifier: Development Status :: 3 - Alpha
Classifier: Intended Audience :: Developers
Classifier: Topic :: Software Development :: Compilers
Classifier: License :: OSI Approved :: Apache Software License
Classifier: Programming Language :: Python :: 3.4
